[{"productId":"6f42329f2b3f4757b890476ea5d56cc2","proNO":"20181119095914848058","proTitle":"邂逅白水寨  感受大自然","proPicUrl":"https://pic.51houniao.com/4a5ad53490d14337bae91d660e01da4c.jpg","collectionNum":444,"sellerUserId":"4bc4027c645343f09a964b5c2e9f875b","sellerUserName":"修罗","amount":225.00,"routingDat":1,"routingNigth":0,"country":"广东省","top":null,"createTime":"2018-11-19 09:59:15","proType":1,"reqId":null,"orderId":null,"reqNo":null,"recommendId":null},{"productId":"71e7a8191f6a417abd9470194a36c1ae","proNO":"20180323155233616515","proTitle":"和风古韵，品味关西旧时光","proPicUrl":"https://pic.51houniao.com/dda7c8e9cb6148339e7a2cdfe8f375b9.jpg","collectionNum":120,"sellerUserId":"4bc4027c645343f09a964b5c2e9f875b","sellerUserName":"修罗","amount":13318.00,"routingDat":6,"routingNigth":5,"country":"日本","top":null,"createTime":"2018-03-23 15:53:51","proType":1,"reqId":null,"orderId":null,"reqNo":null,"recommendId":null},{"productId":"728dbca0f1444be2b60f8355cc9fedce","proNO":"20170223151442469304","proTitle":"爱·普吉 面朝大海春暖花开","proPicUrl":"https://pic.51houniao.com/d0c625023b484be68be7713a98903904.jpg","collectionNum":360,"sellerUserId":"4bc4027c645343f09a964b5c2e9f875b","sellerUserName":"修罗","amount":14654.00,"routingDat":7,"routingNigth":5,"country":"泰国","top":null,"createTime":"2017-02-24 15:54:22","proType":1,"reqId":null,"orderId":null,"reqNo":null,"recommendId":null},{"productId":"728e0d8bf10040759f5657e9da856ba8","proNO":"20190218174953961883","proTitle":"雪域高原  三生三世十里桃花","proPicUrl":"https://pic.51houniao.com/6914eb9f12e64032a528915d299cf982.jpg","collectionNum":1,"sellerUserId":"4bc4027c645343f09a964b5c2e9f875b","sellerUserName":"修罗","amount":13570.00,"routingDat":7,"routingNigth":6,"country":"西藏","top":null,"createTime":"2019-02-18 17:49:54","proType":1,"reqId":null,"orderId":null,"reqNo":null,"recommendId":null},{"productId":"7333e1152552466daab49e5e380f0845","proNO":"20170714165306263617","proTitle":"走进硅谷 企业家的梦想之地","proPicUrl":"https://pic.51houniao.com/c6d4347f282a4a34a8469bdb1f5fc7a7.jpg","collectionNum":150,"sellerUserId":"4bc4027c645343f09a964b5c2e9f875b","sellerUserName":"修罗","amount":28654.00,"routingDat":8,"routingNigth":6,"country":"美国","top":null,"createTime":"2017-08-14 11:41:42","proType":1,"reqId":null,"orderId":null,"reqNo":null,"recommendId":null},{"productId":"733fd6adaacb430a8db26b1bc47dff8d","proNO":"20181225175330999083","proTitle":"拓展丨七星岩 古宋城墙","proPicUrl":"https://pic.51houniao.com/d259b1429d214da6b0918212485b1452.jpg","collectionNum":1,"sellerUserId":"4bc4027c645343f09a964b5c2e9f875b","sellerUserName":"修罗","amount":603.00,"routingDat":2,"routingNigth":1,"country":"广东省","top":null,"createTime":"2018-12-25 17:53:31","proType":1,"reqId":null,"orderId":null,"reqNo":null,"recommendId":null}]